odoo/addons/web_session_auto_close/README.rst
odoo/addons/web_session_auto_close/__init__.py
odoo/addons/web_session_auto_close/__manifest__.py
odoo/addons/web_session_auto_close/controllers/__init__.py
odoo/addons/web_session_auto_close/controllers/main.py
odoo/addons/web_session_auto_close/i18n/it.po
odoo/addons/web_session_auto_close/i18n/web_session_auto_close.pot
odoo/addons/web_session_auto_close/models/__init__.py
odoo/addons/web_session_auto_close/models/res_config_settings.py
odoo/addons/web_session_auto_close/readme/CONFIGURE.md
odoo/addons/web_session_auto_close/readme/CONTRIBUTORS.md
odoo/addons/web_session_auto_close/readme/DESCRIPTION.md
odoo/addons/web_session_auto_close/static/description/icon.png
odoo/addons/web_session_auto_close/static/description/index.html
odoo/addons/web_session_auto_close/static/src/js/session_auto_close.esm.js
odoo/addons/web_session_auto_close/views/res_config_settings.xml
odoo_addon_web_session_auto_close-18.0.1.0.1.dist-info/METADATA
odoo_addon_web_session_auto_close-18.0.1.0.1.dist-info/WHEEL
odoo_addon_web_session_auto_close-18.0.1.0.1.dist-info/top_level.txt
odoo_addon_web_session_auto_close-18.0.1.0.1.dist-info/RECORD
